<?xml version="1.0"?>
<Complete_Units_Ground_War>


	<GroundWarFormation Name="UNIT_GW_HAPES_AAA">
		<Variant_Of_Existing_Type>GroundWar_Spawner_Unit</Variant_Of_Existing_Type>
		<Affiliation>Hapes_Consortium</Affiliation>
		
		<Text_ID>GW_HAPES_AAA</Text_ID>
		<Encyclopedia_Unit_Class>TEXT_ENCYCLOPEDIA_CLASS_GROUP_SPAWNER</Encyclopedia_Unit_Class>
		
		<Land_Model_Name>GROUNDWAR_Hapan.alo</Land_Model_Name>
		<Icon_Name>i_button_guard_galney.tga</Icon_Name>
		<Scale_Factor>1.0</Scale_Factor>

		<Lua_Script></Lua_Script>
		<Tech_Level>99</Tech_Level>
		
		<Starting_Spawned_Units_Tech_0>Template_GroundWar_Spawner_Hapan_Infantry_Squad_Deployed, 2</Starting_Spawned_Units_Tech_0>
		<Starting_Spawned_Units_Tech_0>Template_GroundWar_Spawner_Galney_Infantry_Squad_Deployed, 3</Starting_Spawned_Units_Tech_0>


			
		<!--<MULTIPLAYER SKIRMISH VALUES BEGIN>-->
		<Tactical_Build_Cost_Multiplayer>1</Tactical_Build_Cost_Multiplayer>
		<Tactical_Build_Time_Seconds>1</Tactical_Build_Time_Seconds>
		<Tactical_Build_Prerequisites></Tactical_Build_Prerequisites>
		<Tactical_Production_Queue>Tactical_Units</Tactical_Production_Queue>
		<!--<Build_Limit_Current_Per_Player>0</Build_Limit_Current_Per_Player>-->
		<!--<Build_Limit_Lifetime_Per_Player>0</Build_Limit_Lifetime_Per_Player>-->

	</GroundWarFormation>
	
	<GroundWarFormation Name="UNIT_GW_HAPES_AAB">
		<Variant_Of_Existing_Type>GroundWar_Spawner_Unit</Variant_Of_Existing_Type>
		<Affiliation>Hapes_Consortium</Affiliation>
		
		<Text_ID>GW_HAPES_AAB</Text_ID>
		<Encyclopedia_Unit_Class>TEXT_ENCYCLOPEDIA_CLASS_GROUP_SPAWNER</Encyclopedia_Unit_Class>
		
		<Land_Model_Name>GROUNDWAR_Hapan.alo</Land_Model_Name>
		<Icon_Name>i_button_guard_hapes.tga</Icon_Name>
		<Scale_Factor>1.0</Scale_Factor>

		<Lua_Script></Lua_Script>
		<Tech_Level>99</Tech_Level>
		
		<Starting_Spawned_Units_Tech_0>Template_GroundWar_Spawner_Hapan_Infantry_Squad_Deployed, 3</Starting_Spawned_Units_Tech_0>
	

			
		<!--<MULTIPLAYER SKIRMISH VALUES BEGIN>-->
		<Tactical_Build_Cost_Multiplayer>1</Tactical_Build_Cost_Multiplayer>
		<Tactical_Build_Time_Seconds>1</Tactical_Build_Time_Seconds>
		<Tactical_Build_Prerequisites></Tactical_Build_Prerequisites>
		<Tactical_Production_Queue>Tactical_Units</Tactical_Production_Queue>
		<!--<Build_Limit_Current_Per_Player>0</Build_Limit_Current_Per_Player>-->
		<!--<Build_Limit_Lifetime_Per_Player>0</Build_Limit_Lifetime_Per_Player>-->

	</GroundWarFormation>
	
	<GroundWarFormation Name="UNIT_GW_HAPES_AAC">
		<Variant_Of_Existing_Type>GroundWar_Spawner_Unit</Variant_Of_Existing_Type>
		<Affiliation>Hapes_Consortium</Affiliation>
		
		<Text_ID>GW_HAPES_AAC</Text_ID>
		<Encyclopedia_Unit_Class>TEXT_ENCYCLOPEDIA_CLASS_GROUP_SPAWNER</Encyclopedia_Unit_Class>
		
		<Land_Model_Name>GROUNDWAR_Hapan.alo</Land_Model_Name>
		<Icon_Name>i_button_hapan_ground_transport.tga</Icon_Name>
		<Scale_Factor>1.0</Scale_Factor>

		<Lua_Script></Lua_Script>
		<Tech_Level>99</Tech_Level>
		
		<Starting_Spawned_Units_Tech_0>Template_GroundWar_Spawner_Hapan_Ground_Transport, 1</Starting_Spawned_Units_Tech_0>
		<Starting_Spawned_Units_Tech_0>Template_GroundWar_Spawner_Requud_Infantry_Squad_Deployed, 2</Starting_Spawned_Units_Tech_0>
		<Starting_Spawned_Units_Tech_0>Template_GroundWar_Spawner_Galney_Infantry_Squad_Deployed, 2</Starting_Spawned_Units_Tech_0>


			
		<!--<MULTIPLAYER SKIRMISH VALUES BEGIN>-->
		<Tactical_Build_Cost_Multiplayer>1</Tactical_Build_Cost_Multiplayer>
		<Tactical_Build_Time_Seconds>1</Tactical_Build_Time_Seconds>
		<Tactical_Build_Prerequisites></Tactical_Build_Prerequisites>
		<Tactical_Production_Queue>Tactical_Units</Tactical_Production_Queue>
		<!--<Build_Limit_Current_Per_Player>0</Build_Limit_Current_Per_Player>-->
		<!--<Build_Limit_Lifetime_Per_Player>0</Build_Limit_Lifetime_Per_Player>-->

	</GroundWarFormation>

	<GroundWarFormation Name="UNIT_GW_HAPES_AAD">
		<Variant_Of_Existing_Type>GroundWar_Spawner_Unit</Variant_Of_Existing_Type>
		<Affiliation>Hapes_Consortium</Affiliation>
		
		<Text_ID>GW_HAPES_AAD</Text_ID>
		<Encyclopedia_Unit_Class>TEXT_ENCYCLOPEDIA_CLASS_GROUP_SPAWNER</Encyclopedia_Unit_Class>
		
		<Land_Model_Name>GROUNDWAR_Hapan.alo</Land_Model_Name>
		<Icon_Name>I_BUTTON_HAPAN_LIGHT_MECH.tga</Icon_Name>
		<Scale_Factor>1.0</Scale_Factor>

		<Lua_Script></Lua_Script>
		<Tech_Level>99</Tech_Level>
		
		<Starting_Spawned_Units_Tech_0>Template_GroundWar_Spawner_Hapan_LightTank, 3</Starting_Spawned_Units_Tech_0>
		<Starting_Spawned_Units_Tech_0>Template_GroundWar_Spawner_Hapan_Ground_Transport, 2</Starting_Spawned_Units_Tech_0>


			
		<!--<MULTIPLAYER SKIRMISH VALUES BEGIN>-->
		<Tactical_Build_Cost_Multiplayer>1</Tactical_Build_Cost_Multiplayer>
		<Tactical_Build_Time_Seconds>1</Tactical_Build_Time_Seconds>
		<Tactical_Build_Prerequisites></Tactical_Build_Prerequisites>
		<Tactical_Production_Queue>Tactical_Units</Tactical_Production_Queue>
		<!--<Build_Limit_Current_Per_Player>0</Build_Limit_Current_Per_Player>-->
		<!--<Build_Limit_Lifetime_Per_Player>0</Build_Limit_Lifetime_Per_Player>-->

	</GroundWarFormation>

	<GroundWarFormation Name="UNIT_GW_HAPES_AAE">
		<Variant_Of_Existing_Type>GroundWar_Spawner_Unit</Variant_Of_Existing_Type>
		<Affiliation>Hapes_Consortium</Affiliation>
		
		<Text_ID>GW_HAPES_AAE</Text_ID>
		<Encyclopedia_Unit_Class>TEXT_ENCYCLOPEDIA_CLASS_GROUP_SPAWNER</Encyclopedia_Unit_Class>
		
		<Land_Model_Name>GROUNDWAR_Hapan.alo</Land_Model_Name>
		<Icon_Name>i_button_rgc_commando.tga</Icon_Name>
		<Scale_Factor>1.0</Scale_Factor>

		<Lua_Script></Lua_Script>
		<Tech_Level>99</Tech_Level>
		
		<Starting_Spawned_Units_Tech_0>Template_GroundWar_Spawner_HRG_Commando_Assault_Team_Deployed, 3</Starting_Spawned_Units_Tech_0>
		<Starting_Spawned_Units_Tech_0>Template_GroundWar_Spawner_Galney_Infantry_Squad_Deployed, 3</Starting_Spawned_Units_Tech_0>
		<Starting_Spawned_Units_Tech_0>Template_GroundWar_Spawner_HRG_Commando_Heavy_Team_Deployed, 2</Starting_Spawned_Units_Tech_0>
		<Starting_Spawned_Units_Tech_0>Template_GroundWar_Spawner_HRG_Commando_Sniper_Team_Deployed, 1</Starting_Spawned_Units_Tech_0>


			
		<!--<MULTIPLAYER SKIRMISH VALUES BEGIN>-->
		<Tactical_Build_Cost_Multiplayer>1</Tactical_Build_Cost_Multiplayer>
		<Tactical_Build_Time_Seconds>1</Tactical_Build_Time_Seconds>
		<Tactical_Build_Prerequisites></Tactical_Build_Prerequisites>
		<Tactical_Production_Queue>Tactical_Units</Tactical_Production_Queue>
		<!--<Build_Limit_Current_Per_Player>0</Build_Limit_Current_Per_Player>-->
		<!--<Build_Limit_Lifetime_Per_Player>0</Build_Limit_Lifetime_Per_Player>-->

	</GroundWarFormation>
	
	<GroundWarFormation Name="UNIT_GW_HAPES_AAF">
		<Variant_Of_Existing_Type>GroundWar_Spawner_Unit</Variant_Of_Existing_Type>
		<Affiliation>Hapes_Consortium</Affiliation>
		
		<Text_ID>GW_HAPES_AAF</Text_ID>
		<Encyclopedia_Unit_Class>TEXT_ENCYCLOPEDIA_CLASS_GROUP_SPAWNER</Encyclopedia_Unit_Class>
		
		<Land_Model_Name>GROUNDWAR_Hapan.alo</Land_Model_Name>
		<Icon_Name>i_button_guard_maluri_support.tga</Icon_Name>
		<Scale_Factor>1.0</Scale_Factor>

		<Lua_Script></Lua_Script>
		<Tech_Level>99</Tech_Level>
		
		<Starting_Spawned_Units_Tech_0>Template_GroundWar_Spawner_Hapan_Infantry_Squad_Deployed, 4</Starting_Spawned_Units_Tech_0>
		<Starting_Spawned_Units_Tech_0>Template_GroundWar_Spawner_Maluri_Infantry_Support_Squad_Deployed, 2</Starting_Spawned_Units_Tech_0>


			
		<!--<MULTIPLAYER SKIRMISH VALUES BEGIN>-->
		<Tactical_Build_Cost_Multiplayer>1</Tactical_Build_Cost_Multiplayer>
		<Tactical_Build_Time_Seconds>1</Tactical_Build_Time_Seconds>
		<Tactical_Build_Prerequisites></Tactical_Build_Prerequisites>
		<Tactical_Production_Queue>Tactical_Units</Tactical_Production_Queue>
		<!--<Build_Limit_Current_Per_Player>0</Build_Limit_Current_Per_Player>-->
		<!--<Build_Limit_Lifetime_Per_Player>0</Build_Limit_Lifetime_Per_Player>-->

	</GroundWarFormation>
	
	<GroundWarFormation Name="UNIT_GW_HAPES_AAG">
		<Variant_Of_Existing_Type>GroundWar_Spawner_Unit</Variant_Of_Existing_Type>
		<Affiliation>Hapes_Consortium</Affiliation>
		
		<Text_ID>GW_HAPES_AAG</Text_ID>
		<Encyclopedia_Unit_Class>TEXT_ENCYCLOPEDIA_CLASS_GROUP_SPAWNER</Encyclopedia_Unit_Class>
		
		<Land_Model_Name>GROUNDWAR_Hapan.alo</Land_Model_Name>
		<Icon_Name>i_button_silanus.tga</Icon_Name>
		<Scale_Factor>1.0</Scale_Factor>

		<Lua_Script></Lua_Script>
		<Tech_Level>99</Tech_Level>
		
		<Starting_Spawned_Units_Tech_0>Template_GroundWar_Spawner_Hapan_Silanus, 4</Starting_Spawned_Units_Tech_0>
		
			
		<!--<MULTIPLAYER SKIRMISH VALUES BEGIN>-->
		<Tactical_Build_Cost_Multiplayer>1</Tactical_Build_Cost_Multiplayer>
		<Tactical_Build_Time_Seconds>1</Tactical_Build_Time_Seconds>
		<Tactical_Build_Prerequisites></Tactical_Build_Prerequisites>
		<Tactical_Production_Queue>Tactical_Units</Tactical_Production_Queue>
		<!--<Build_Limit_Current_Per_Player>0</Build_Limit_Current_Per_Player>-->
		<!--<Build_Limit_Lifetime_Per_Player>0</Build_Limit_Lifetime_Per_Player>-->

	</GroundWarFormation>

	<GroundWarFormation Name="UNIT_GW_HAPES_AAH">
		<Variant_Of_Existing_Type>GroundWar_Spawner_Unit</Variant_Of_Existing_Type>
		<Affiliation>Hapes_Consortium</Affiliation>
		
		<Text_ID>GW_HAPES_AAH</Text_ID>
		<Encyclopedia_Unit_Class>TEXT_ENCYCLOPEDIA_CLASS_GROUP_SPAWNER</Encyclopedia_Unit_Class>
		
		<Land_Model_Name>GROUNDWAR_Hapan.alo</Land_Model_Name>
		<Icon_Name>I_BUTTON_HAPAN_HEAVY_MECH.tga</Icon_Name>
		<Scale_Factor>1.0</Scale_Factor>

		<Lua_Script></Lua_Script>
		<Tech_Level>99</Tech_Level>
		
		<Starting_Spawned_Units_Tech_0>Template_GroundWar_Spawner_Hapan_HeavyTank, 2</Starting_Spawned_Units_Tech_0>
		<Starting_Spawned_Units_Tech_0>Template_GroundWar_Spawner_Hapan_LightTank, 3</Starting_Spawned_Units_Tech_0>


			
		<!--<MULTIPLAYER SKIRMISH VALUES BEGIN>-->
		<Tactical_Build_Cost_Multiplayer>1</Tactical_Build_Cost_Multiplayer>
		<Tactical_Build_Time_Seconds>1</Tactical_Build_Time_Seconds>
		<Tactical_Build_Prerequisites></Tactical_Build_Prerequisites>
		<Tactical_Production_Queue>Tactical_Units</Tactical_Production_Queue>
		<!--<Build_Limit_Current_Per_Player>0</Build_Limit_Current_Per_Player>-->
		<!--<Build_Limit_Lifetime_Per_Player>0</Build_Limit_Lifetime_Per_Player>-->

	</GroundWarFormation>

	<GroundWarFormation Name="UNIT_GW_HAPES_AAI">
		<Variant_Of_Existing_Type>GroundWar_Spawner_Unit</Variant_Of_Existing_Type>
		<Affiliation>Hapes_Consortium</Affiliation>
		
		<Text_ID>GW_HAPES_AAI</Text_ID>
		<Encyclopedia_Unit_Class>TEXT_ENCYCLOPEDIA_CLASS_GROUP_SPAWNER</Encyclopedia_Unit_Class>
		
		<Land_Model_Name>GROUNDWAR_Hapan.alo</Land_Model_Name>
		<Icon_Name>i_button_hapan_artillery.tga</Icon_Name>
		<Scale_Factor>1.0</Scale_Factor>

		<Lua_Script></Lua_Script>
		<Tech_Level>99</Tech_Level>
		
		<Starting_Spawned_Units_Tech_0>Template_GroundWar_Spawner_Hapan_Artillery, 1</Starting_Spawned_Units_Tech_0>
		<Starting_Spawned_Units_Tech_0>Template_GroundWar_Spawner_Hapan_Infantry_Squad_Deployed, 3</Starting_Spawned_Units_Tech_0>
		

			
		<!--<MULTIPLAYER SKIRMISH VALUES BEGIN>-->
		<Tactical_Build_Cost_Multiplayer>1</Tactical_Build_Cost_Multiplayer>
		<Tactical_Build_Time_Seconds>1</Tactical_Build_Time_Seconds>
		<Tactical_Build_Prerequisites></Tactical_Build_Prerequisites>
		<Tactical_Production_Queue>Tactical_Units</Tactical_Production_Queue>
		<!--<Build_Limit_Current_Per_Player>0</Build_Limit_Current_Per_Player>-->
		<!--<Build_Limit_Lifetime_Per_Player>0</Build_Limit_Lifetime_Per_Player>-->

	</GroundWarFormation>

	
	<GroundWarFormation Name="UNIT_GW_HAPES_AAJ">
		<Variant_Of_Existing_Type>GroundWar_Spawner_Unit</Variant_Of_Existing_Type>
		<Affiliation>Hapes_Consortium</Affiliation>
		
		<Text_ID>GW_HAPES_AAJ</Text_ID>
		<Encyclopedia_Unit_Class>TEXT_ENCYCLOPEDIA_CLASS_GROUP_SPAWNER</Encyclopedia_Unit_Class>
		
		<Land_Model_Name>GROUNDWAR_Hapan.alo</Land_Model_Name>
		<Icon_Name>I_BUTTON_HAPAN_GUNSHIP.tga</Icon_Name>
		<Scale_Factor>1.0</Scale_Factor>

		<Lua_Script></Lua_Script>
		<Tech_Level>99</Tech_Level>
		
		<Starting_Spawned_Units_Tech_0>Template_GroundWar_Spawner_Hapan_Gunboat, 2</Starting_Spawned_Units_Tech_0>
		<Starting_Spawned_Units_Tech_0>Template_GroundWar_Spawner_Hapan_Silanus, 6</Starting_Spawned_Units_Tech_0>


			
		<!--<MULTIPLAYER SKIRMISH VALUES BEGIN>-->
		<Tactical_Build_Cost_Multiplayer>1</Tactical_Build_Cost_Multiplayer>
		<Tactical_Build_Time_Seconds>1</Tactical_Build_Time_Seconds>
		<Tactical_Build_Prerequisites></Tactical_Build_Prerequisites>
		<Tactical_Production_Queue>Tactical_Units</Tactical_Production_Queue>
		<!--<Build_Limit_Current_Per_Player>0</Build_Limit_Current_Per_Player>-->
		<!--<Build_Limit_Lifetime_Per_Player>0</Build_Limit_Lifetime_Per_Player>-->

	</GroundWarFormation>
	
	<GroundWarFormation Name="UNIT_GW_HAPES_AAK">
		<Variant_Of_Existing_Type>GroundWar_Spawner_Unit</Variant_Of_Existing_Type>
		<Affiliation>Hapes_Consortium</Affiliation>
		
		<Text_ID>GW_HAPES_AAK</Text_ID>
		<Encyclopedia_Unit_Class>TEXT_ENCYCLOPEDIA_CLASS_GROUP_SPAWNER</Encyclopedia_Unit_Class>
		
		<Land_Model_Name>GROUNDWAR_Hapan.alo</Land_Model_Name>
		<Icon_Name>i_button_rgc_commando_weap.tga</Icon_Name>
		<Scale_Factor>1.0</Scale_Factor>

		<Lua_Script></Lua_Script>
		<Tech_Level>99</Tech_Level>
		
		<Starting_Spawned_Units_Tech_0>Template_GroundWar_Spawner_HRFG_Gunner_Team_Deployed, 2</Starting_Spawned_Units_Tech_0>
		<Starting_Spawned_Units_Tech_0>Template_GroundWar_Spawner_HRFG_Sniper_Team_Deployed, 2</Starting_Spawned_Units_Tech_0>
		<Starting_Spawned_Units_Tech_0>Template_GroundWar_Spawner_HRG_Commando_Assault_Team_Deployed, 2</Starting_Spawned_Units_Tech_0>
		<Starting_Spawned_Units_Tech_0>Template_GroundWar_Spawner_Galney_Infantry_Squad_Deployed, 4</Starting_Spawned_Units_Tech_0>
		<Starting_Spawned_Units_Tech_0>Template_GroundWar_Spawner_Maluri_Infantry_Support_Squad_Deployed, 1</Starting_Spawned_Units_Tech_0>
		<Starting_Spawned_Units_Tech_0>Template_GroundWar_Spawner_Hapan_Ground_Transport, 2</Starting_Spawned_Units_Tech_0>
		
		<!--<MULTIPLAYER SKIRMISH VALUES BEGIN>-->
		<Tactical_Build_Cost_Multiplayer>1</Tactical_Build_Cost_Multiplayer>
		<Tactical_Build_Time_Seconds>1</Tactical_Build_Time_Seconds>
		<Tactical_Build_Prerequisites></Tactical_Build_Prerequisites>
		<Tactical_Production_Queue>Tactical_Units</Tactical_Production_Queue>
		<!--<Build_Limit_Current_Per_Player>0</Build_Limit_Current_Per_Player>-->
		<!--<Build_Limit_Lifetime_Per_Player>0</Build_Limit_Lifetime_Per_Player>-->

	</GroundWarFormation>
	
	<GroundWarFormation Name="UNIT_GW_HAPES_AAL">
		<Variant_Of_Existing_Type>GroundWar_Spawner_Unit</Variant_Of_Existing_Type>
		<Affiliation>Hapes_Consortium</Affiliation>
		
		<Text_ID>GW_HAPES_AAL</Text_ID>
		<Encyclopedia_Unit_Class>TEXT_ENCYCLOPEDIA_CLASS_GROUP_SPAWNER</Encyclopedia_Unit_Class>
		
		<Land_Model_Name>GROUNDWAR_Hapan.alo</Land_Model_Name>
		<Icon_Name>i_button_rgc_commando_sniper.tga</Icon_Name>
		<Scale_Factor>1.0</Scale_Factor>

		<Lua_Script></Lua_Script>
		<Tech_Level>99</Tech_Level>
		
		<Starting_Spawned_Units_Tech_0>Template_GroundWar_Spawner_Hapan_Gunboat, 3</Starting_Spawned_Units_Tech_0>
		<Starting_Spawned_Units_Tech_0>Template_GroundWar_Spawner_HRFG_Gunner_Team_Deployed, 1</Starting_Spawned_Units_Tech_0>
		<Starting_Spawned_Units_Tech_0>Template_GroundWar_Spawner_HRFG_Sniper_Team_Deployed, 1</Starting_Spawned_Units_Tech_0>
		<Starting_Spawned_Units_Tech_0>Template_GroundWar_Spawner_HRG_Commando_Sniper_Team_Deployed, 2</Starting_Spawned_Units_Tech_0>
		<Starting_Spawned_Units_Tech_0>Template_GroundWar_Spawner_HRG_Commando_Heavy_Team_Deployed, 2</Starting_Spawned_Units_Tech_0>


			
		<!--<MULTIPLAYER SKIRMISH VALUES BEGIN>-->
		<Tactical_Build_Cost_Multiplayer>1</Tactical_Build_Cost_Multiplayer>
		<Tactical_Build_Time_Seconds>1</Tactical_Build_Time_Seconds>
		<Tactical_Build_Prerequisites></Tactical_Build_Prerequisites>
		<Tactical_Production_Queue>Tactical_Units</Tactical_Production_Queue>
		<!--<Build_Limit_Current_Per_Player>0</Build_Limit_Current_Per_Player>-->
		<!--<Build_Limit_Lifetime_Per_Player>0</Build_Limit_Lifetime_Per_Player>-->

	</GroundWarFormation>

</Complete_Units_Ground_War>